{
  "de": {
    "food": {
      "title": "วลีร้านอาหารภาษาเยอรมัน — สั่งอาหาร จ่ายเงิน แจ้งอาการแพ้",
      "subtitle": "สั่งอาหารในร้านอาหาร แจ้งเรื่องอาการแพ้ เรียกบิล และชมเชยพ่อครัว",
      "intro": "การกินอาหารคือวิธีที่เร็วที่สุดในการรู้สึกคุ้นเคยกับภาษาใหม่ ประโยค 10 ประโยคในชุดนี้ครอบคลุมสถานการณ์ 95%: เข้าร้านอาหาร สั่งอาหาร สอบถามเรื่องอาการแพ้ ชำระเงิน และจากไป ไม่ว่าคุณจะนั่งอยู่ที่ผับมุมถนนในเบอร์ลิน คาเฟ่ในเวียนนา ร้านอาหารในซูริก หรือเบียร์การ์เดนในมิวนิก — ขั้นตอนจะเหมือนกัน และระดับความสุภาพก็ค่อนข้างยืดหยุ่น: พนักงานเสิร์ฟในพื้นที่ที่ใช้ภาษาเยอรมันคาดหวังคำถามง่ายๆ และตอบรับได้ดีกับถ้อยคำตรงไปตรงมาแต่สุภาพ ชุดร้านอาหารของ LangOria สร้างขึ้นจาก 10 ประโยคที่คุณจะได้ใช้ทุกครั้งที่ทานอาหารนอกบ้าน",
      "culture": "ในพื้นที่ที่ใช้ภาษาเยอรมัน เป็นธรรมเนียมที่พนักงานเสิร์ฟจะมาหาคุณตั้งแต่แรกเพื่อถามเครื่องดื่ม (« Was darf es sein? » หรือ « Was möchten Sie trinken? ») จากนั้นเขาจะกลับมาอีกครั้งเมื่อเห็นว่าคุณพร้อมแล้ว — หรือคุณส่งสัญญาณด้วยการสบตาเล็กน้อยหรือท่าทางมือเบาๆ ว่าคุณต้องการสั่งอาหาร « Die Rechnung, bitte » หรือ « Zahlen, bitte » เป็นมาตรฐาน ในสวิตเซอร์แลนด์จะพูดว่า « Die Rechnung, bitte » และค่าบริการมักรวมอยู่แล้ว; ในเยอรมนีและออสเตรีย มักจะปัดเศษขึ้นประมาณ 5-10% สำหรับอาการแพ้ ให้แจ้งชัดเจนตั้งแต่แรกว่า « Ich bin allergisch gegen Nüsse » หรือ « Ich bin Vegetarier » — เชฟมักยินดีปรับเปลี่ยนให้ รายละเอียดท้องถิ่นเพิ่มเติม: ในเยอรมนี «Brot» (ขนมปัง) เป็นสิ่งมาตรฐานที่เสิร์ฟพร้อมอาหาร — ในบาวาเรีย («Brotzeit») ถึงขั้นเป็นมื้ออาหารของตัวเองเลย ในออสเตรีย «Wiener Küche» (อาหารเวียนนา) มีชื่อเสียงระดับโลก — Wiener Schnitzel, Sachertorte และ Apfelstrudel คือสามเมนูหลัก «Wiener Schnitzel» ต้องทำจากเนื้อลูกวัวเท่านั้น («Wiener Schnitzel vom Kalb») มิฉะนั้นจะเรียกว่า «Schnitzel Wiener Art» (ทำจากเนื้อหมู) ในสวิตเซอร์แลนด์ ปริมาณอาหารจะน้อยกว่าและราคาสูงกว่าเยอรมนี แต่คุณภาพยอดเยี่ยม — «Fondue», «Raclette», «Rösti» และ «Zürcher Geschnetzeltes» คือเมนูคลาสสิก «Brot» ในสวิตเซอร์แลนด์คือ «Brot» (มาตรฐาน) และเป็นส่วนสำคัญของทุกมื้ออาหาร «Znüni» (คำภาษาสวิสหมายถึงของว่างเวลา 9 โมง จริงๆ คือเวลา 10:00 น.) และ «Zvieri» (ของว่างเวลา 16:00 น.) เป็นประเพณีของสวิตเซอร์แลนด์ ในเยอรมนีและออสเตรีย «Sperrstunde» (เวลาห้ามขายแอลกอฮอล์) จะแตกต่างกันตามภูมิภาค — เบอร์ลินขายแอลกอฮอล์ได้ตลอด 24 ชั่วโมง ส่วนบาวาเรียมีเวลาประมาณ 22:00 น. ในออสเตรีย หน้าร้อนมักสั่ง «einen Eiskaffee» (กาแฟเย็นใส่น้ำแข็งและวิปครีม) — เป็นที่นิยมมาก ในเยอรมนี «Bier» (เบียร์) ถือเป็นอาหารหลัก — กฎหมาย Reinheitsgebot (Reinheitsgebot, ค.ศ.1516) รับประกันว่าเบียร์ทำจากฮอปส์ มอลต์ น้ำ และยีสต์เท่านั้น «Prost!» เป็นคำอวยพรเวลาดื่มมาตรฐาน — ต้องพูดว่า «Prost» พร้อมสบตากันด้วย «Schnaps» (เหล้าผลไม้หรือเหล้าสมุนไพร) มักเสิร์ฟหลังอาหาร — การดื่ม «einen Schnaps» เพื่อช่วยย่อยเป็นเรื่องปกติ",
      "howTo": "ใช้เวลา 2-3 วันฝึกชุดร้านอาหารก่อนไปร้านอาหารทุกครั้ง ฝึกบทสนทนาดังๆ กับเพื่อนหรืออัดเสียงไว้; ภาษาเยอรมันสำหรับร้านอาหารเป็นเรื่องของความจำแบบกล้ามเนื้อ ไม่ใช่ไวยากรณ์ เมื่อคุณเข้าร้านอาหาร ให้มีสคริปต์ชัดเจน: « Einen Tisch für [X], bitte » → « Kann ich die Speisekarte sehen? » → « Ich nehme [X], bitte » → « Die Rechnung, bitte » → « Das war köstlich, danke ». แค่ฝึกวันละ 10 นาทีก็เพียงพอแล้ว ลองทำแบบฝึกหัด 3 อย่างนี้: (1) ก่อนกินอาหาร — เปิดชุดนี้ ฟังเสียง 2 รอบ แล้วหลับตาท่อง 10 ประโยคตามลำดับจากความจำ (2) ขณะกินอาหาร — ลองใช้ประโยคที่คุณยังไม่เคยใช้จริง เช่น « Ist dieses Gericht scharf? » แม้คุณจะไม่ได้สั่งแกงกะหรี่ ก็ใช้เพื่อเริ่มบทสนทนากับพนักงานเสิร์ฟ (3) หลังกินอาหาร — จดประโยคที่ทำให้คุณแปลกใจ (เรื่องทิป? ความต่างระหว่าง « Rechnung » กับ « Quittung »?) แล้วเพิ่มลงในชุด spaced-repetition ของคุณ ภายในสัปดาห์แรก คุณควรสั่งอาหาร เปลี่ยนเมนู และจ่ายเงินได้โดยไม่ต้องแปลในใจ; ภายในเดือนแรก คุณควรตอบคำถามที่ไม่คาดคิดจากพนักงานเสิร์ฟได้คล่อง (เรื่องอาการแพ้ คำแนะนำไวน์ หรือเมนูพิเศษนอกเมนู)",
      "phrases": [
        {
          "index": 0,
          "en": "Could I see the menu, please?"
        },
        {
          "index": 1,
          "en": "What do you recommend?"
        },
        {
          "index": 2,
          "en": "I'm allergic to [X]."
        },
        {
          "index": 3,
          "en": "Could I have the bill, please?"
        },
        {
          "index": 4,
          "en": "Is this dish spicy?"
        },
        {
          "index": 5,
          "en": "I'll have [X], please."
        },
        {
          "index": 6,
          "en": "Can I get this to go?"
        },
        {
          "index": 7,
          "en": "Is the tip included?"
        },
        {
          "index": 8,
          "en": "I'm a vegetarian."
        },
        {
          "index": 9,
          "en": "That was delicious, thank you."
        }
      ],
      "conversation": [
        {
          "index": 0,
          "en": "Hi, table for two, please."
        },
        {
          "index": 1,
          "en": "Of course. Right this way. Here's the menu."
        },
        {
          "index": 2,
          "en": "Thank you. What do you recommend?"
        },
        {
          "index": 3,
          "en": "The fish is excellent today. Are you allergic to anything?"
        }
      ]
    }
  }
}
