{
  "de": {
    "food": {
      "title": "독일어 레스토랑 문구 — 주문, 결제, 알레르기",
      "subtitle": "레스토랑에서 주문하고, 알레르기를 알리고, 계산서를 요청하고, 요리사에게 칭찬하기.",
      "intro": "음식은 새로운 언어에 익숙해지는 가장 빠른 방법입니다. 이 세트의 10가지 문장은 95%의 경우를 다룹니다: 레스토랑에 들어가기, 주문하기, 알레르기 문의하기, 결제하기, 그리고 떠나기. 베를린의 동네 술집, 비엔나의 카페, 취리히의 레스토랑, 뮌헨의 비어 가든 어디에 앉아 있든 — 과정은 동일하며, 예의 수준은 관대합니다: 독일어권 웨이터들은 간단한 질문을 예상하며 직접적이고 정중한 언어에 잘 반응합니다. LangOria의 레스토랑 세트는 외식할 때마다 나오는 10가지 문장을 중심으로 구성되어 있습니다.",
      "culture": "독일어권에서는 웨이터가 처음에 와서 음료를 묻는 것이 일반적입니다(« 무엇을 드릴까요? » 또는 « 무엇을 마시고 싶으세요? »). 웨이터는 손님이 준비되었다고 판단할 때까지 다시 오지 않거나, 손님이 가벼운 눈맞춤이나 discreet한 손짓으로 주문하고 싶다는 신호를 보낼 때 옵니다. « 계산서 주세요 » 또는 « 계산할게요 »는 표준입니다. 스위스에서는 « 계산서 주세요 »라고 말하며 서비스 요금이 포함되는 경우가 많습니다; 독일과 오스트리아에서는 5-10%를 반올림하여 팁을 줍니다. 알레르기가 있다면 처음에 명확하게 말하세요: « 저는 견과류 알레르기가 있습니다 » 또는 « 저는 채식주의자입니다 » — 요리사들은 기꺼이 맞춰줍니다. 추가적인 지역별 세부 사항: 독일에서는 식사와 함께 « 빵 »이 기본입니다 — 바이에른(« Brotzeit »)에서는 심지어 그 자체가 식사입니다. 오스트리아에서는 « 비엔나 요리 »가 세계적으로 유명합니다 — 비엔나 슈니첼, 자허토르테, 아펠슈트루델이 세 가지 주요 요리입니다. « 비엔나 슈니첼 »은 송아지 고기로 만들어져야 합니다(« 송아지 고기 비엔나 슈니첼 »), 그렇지 않으면 « 비엔나 스타일 슈니첼 »(돼지고기)입니다. 스위스에서는 독일보다 양이 적고 가격이 높지만 품질은 훌륭합니다 — « 퐁듀 », « 라클레트 », « 뢰스티 », « 취리히식 송아지 고기 요리 »가 대표적입니다. 스위스에서 « 빵 »은 « 빵 »(기본)이며 모든 식사의 주요 구성 요소입니다. « Znüni »(스위스 독일어로 « 9시 »를 의미하며 오전 10시 간식)와 « Zvieri »(오후 4시 간식)는 스위스 전통입니다. 독일과 오스트리아에서는 « 통행금지 시간 »(Sperrstunde, 주류 판매 마감 시간)이 지역마다 다릅니다 — 베를린은 24시간 주류 판매가 가능하며, 바이에른은 오후 10시가 기준입니다. 오스트리아에서는 여름에 « 아이스커피 »(아이스크림 + 커피 + 크림)를 주문하는데 — 매우 인기가 많습니다. 독일에서 « 맥주 »는 주식입니다 — 순수령(Reinheitsgebot, 1516)은 맥주가 홉, 맥아, 물, 효모로만 구성되어 있음을 보장합니다. « 건배! »는 표준 건배사입니다 — « 건배 »와 눈맞춤은 필수입니다. « 슈냅스 »(과일 브랜디, 허브 리큐어)는 식사 후에 제공됩니다 — 소화를 돕는 « 슈냅스 » 한 잔이 흔합니다.",
      "howTo": "레스토랑에 가기 전에 2-3일 동안 레스토랑 세트에 집중하세요. 파트너나 녹음과 함께 대화를 소리 내어 연습하세요; 레스토랑 독일어는 문법이 아니라 근육 기억입니다. 현재로서는 명확한 스크립트를 가지고 들어갑니다: « [X]명 테이블 부탁합니다 » → « 메뉴판 좀 볼 수 있을까요? » → « [X]로 주세요 » → « 계산서 주세요 » → « 맛있었습니다, 감사합니다 ». 매일 10분 루틴이면 충분합니다. 세 가지 구체적인 연습: (1) 식사 전 — 세트를 열고 오디오를 두 번 듣고, 눈을 감고 10가지 문장을 순서대로 기억해서 재현합니다. (2) 식사 중 — 아직 실생활에서 사용해 보지 않은 문장을 시도해 보세요. 예를 들어, 카레를 주문하지 않더라도 웨이터와 어색함을 깨기 위해 « 이 요리는 매운가요? »라고 말해보세요. (3) 식사 후 — 당신을 놀라게 한 문장(팁 계산서? « Rechnung » vs « Quittung »?)을 기록하고 간격 반복 학습 세트에 추가하세요. 첫 주가 끝날 때쯤에는 머릿속으로 번역하지 않고도 주문하고, 변경하고, 결제할 수 있어야 합니다; 첫 달이 끝날 때쯤에는 웨이터가 예상치 못한 질문(알레르기, 와인 추천, 메뉴 외 추천)을 하더라도 당황하지 않아야 합니다.",
      "phrases": [
        {
          "index": 0,
          "en": "메뉴판 좀 볼 수 있을까요?"
        },
        {
          "index": 1,
          "en": "무엇을 추천하시나요?"
        },
        {
          "index": 2,
          "en": "저는 [X]에 알레르기가 있습니다."
        },
        {
          "index": 3,
          "en": "계산서 좀 주시겠어요?"
        },
        {
          "index": 4,
          "en": "이 요리는 매운가요?"
        },
        {
          "index": 5,
          "en": "[X]로 주세요."
        },
        {
          "index": 6,
          "en": "이것 포장해 갈 수 있을까요?"
        },
        {
          "index": 7,
          "en": "팁이 포함되어 있나요?"
        },
        {
          "index": 8,
          "en": "저는 채식주의자입니다."
        },
        {
          "index": 9,
          "en": "정말 맛있었습니다, 감사합니다."
        }
      ],
      "conversation": [
        {
          "index": 0,
          "en": "안녕하세요, 두 명 테이블 부탁합니다."
        },
        {
          "index": 1,
          "en": "네, 이쪽으로 오세요. 메뉴판 여기 있습니다."
        },
        {
          "index": 2,
          "en": "감사합니다. 무엇을 추천하시나요?"
        },
        {
          "index": 3,
          "en": "오늘 생선 요리가 아주 좋습니다. 알레르기 있으신가요?"
        }
      ]
    }
  }
}
